cdf/__init__.py
cdf/builtin/filters.py
cdf/builtin/metrics.py
cdf/core/__init__.py
cdf/core/component/__init__.py
cdf/core/component/base.py
cdf/core/component/operation.py
cdf/core/component/pipeline.py
cdf/core/component/publisher.py
cdf/core/component/service.py
cdf/core/configuration.py
cdf/core/context.py
cdf/core/injector/__init__.py
cdf/core/injector/errors.py
cdf/core/injector/registry.py
cdf/core/workspace.py
cdf/integrations/__init__.py
cdf/integrations/feature_flag/__init__.py
cdf/integrations/feature_flag/base.py
cdf/integrations/feature_flag/file.py
cdf/integrations/feature_flag/harness.py
cdf/integrations/feature_flag/launchdarkly.py
cdf/integrations/feature_flag/noop.py
cdf/integrations/feature_flag/split.py
cdf/integrations/slack.py
cdf/proxy/__init__.py
cdf/proxy/mysql.py
cdf/proxy/planner.py
cdf/types/__init__.py
cdf/types/monads.py
python_cdf-0.9.4.dist-info/LICENSE
python_cdf-0.9.4.dist-info/METADATA
python_cdf-0.9.4.dist-info/WHEEL
python_cdf-0.9.4.dist-info/RECORD
