Metadata-Version: 2.3
Name: python-cdf
Version: 0.9.4
Summary: A framework to manage data continuously
License: Apache License
Author: z3z1ma
Author-email: butler.alex2010@gmail.com
Requires-Python: >=3.9,<3.13
Classifier: License :: Other/Proprietary License
Classifier: Programming Language :: Python :: 3
Classifier: Programming Language :: Python :: 3.9
Classifier: Programming Language :: Python :: 3.10
Classifier: Programming Language :: Python :: 3.11
Classifier: Programming Language :: Python :: 3.12
Provides-Extra: dev
Requires-Dist: dlt[duckdb]
Requires-Dist: duckdb
Requires-Dist: dynaconf (>=3,<4)
Requires-Dist: eval_type_backport (>=0.1.3,<0.2.0) ; python_version < "3.10"
Requires-Dist: fsspec (>=2022)
Requires-Dist: harness-featureflags (>=1.2.0,<1.6.1)
Requires-Dist: mysql-mimic (>=2,<3)
Requires-Dist: pex (>=2.1.100,<2.2.0)
Requires-Dist: psutil (>=5.9.0,<5.10.0)
Requires-Dist: pydantic (>=2.5.0,<3)
Requires-Dist: pydoc-markdown (>4) ; extra == "dev"
Requires-Dist: pytest (>=7.4.3) ; extra == "dev"
Requires-Dist: pytest-mock (>=3.12.0) ; extra == "dev"
Requires-Dist: python-dotenv (>=1,<2)
Requires-Dist: sqlmesh
Requires-Dist: typing-extensions (>=4,<5)
